README.rst
setup.py
evarify/__init__.py
evarify/evar.py
evarify.egg-info/PKG-INFO
evarify.egg-info/SOURCES.txt
evarify.egg-info/dependency_links.txt
evarify.egg-info/requires.txt
evarify.egg-info/top_level.txt
evarify/filters/__init__.py
evarify/filters/python_basics.py