Metadata-Version: 1.1
Name: evarify
Version: 0.1.1
Summary: Environment variable validation and coercion.
Home-page: https://github.com/gtaylor/evarify
Author: Greg Taylor
Author-email: gtaylor@gc-taylor.com
License: MIT License
Keywords: environment variable
Platform: UNKNOWN
Classifier: Development Status :: 2 - Pre-Alpha
Classifier: Intended Audience :: System Administrators
Classifier: Intended Audience :: Developers
Classifier: License :: OSI Approved :: MIT License
Classifier: Programming Language :: Python :: 2.7
Classifier: Programming Language :: Python :: 3.3
Classifier: Programming Language :: Python :: 3.4
Classifier: Programming Language :: Python :: 3.5
